setup.py
google_actions.egg-info/PKG-INFO
google_actions.egg-info/SOURCES.txt
google_actions.egg-info/dependency_links.txt
google_actions.egg-info/not-zip-safe
google_actions.egg-info/top_level.txt
googleactions/__init__.py
googleactions/builders.py
googleactions/models.py
googleactions/test.py
googleactions/utils.py