Metadata-Version: 1.0
Name: google-actions
Version: 1.0.0
Summary: Client library for Actions on Google using python
Home-page: https://github.com/caycewilliams/actions-on-google-python
Author: Cayce Williams
Author-email: caycewilliams77@gmail.com
License: MIT
Platform: UNKNOWN
